{"version":1621224000,"workloads":{"edd357f0-91c0-58d6-9848-293a02e6c8b2":{"protocol":"HTTP","service":"zk-client/zk-operator","trace_role":"server","conditional_rule":{"condition":"AND","rules":[{"id":"req_method","field":"req_method","type":"string","input":"string","operator":"equal","value":"POST"},{"id":"req_path","field":"req_path","type":"string","input":"string","operator":"ends_with","value":"/exception"}]}}},"filter_id":"1","filters":{"type":"workload","condition":"AND","workload_id_set":["edd357f0-91c0-58d6-9848-293a02e6c8b2"]}}
{"version":1681624000,"workloads":{"2eeaed49-d1a7-526a-9b0b-2e3a01dfa62b":{"protocol":"HTTP","service":"*/*","trace_role":"server","conditional_rule":{"condition":"AND","rules":[{"id":"resp_status","field":"resp_status","type":"integer","input":"integer","operator":"not equal","value":200}]}}},"filter_id":"2","filters":{"type":"workload","condition":"OR","workload_id_set":["2eeaed49-d1a7-526a-9b0b-2e3a01dfa62b"]}}